BioMetAll-1.0.dist-info/DESCRIPTION.rst
BioMetAll-1.0.dist-info/METADATA
BioMetAll-1.0.dist-info/RECORD
BioMetAll-1.0.dist-info/WHEEL
BioMetAll-1.0.dist-info/entry_points.txt
BioMetAll-1.0.dist-info/metadata.json
BioMetAll-1.0.dist-info/top_level.txt
biometall/.DS_Store
biometall/__init__.py
biometall/__main__.py
biometall/_version.py
biometall/biometall.py
biometall/data/README.md
biometall/data/look_and_say.dat
biometall/modules/__init__.py
biometall/modules/box.py
biometall/modules/data.py
biometall/modules/grid.py
biometall/modules/motif.py
biometall/modules/pdb.py
biometall/mol_files/4dc8.mol2
biometall/mol_files/protein_with_H.mol2
biometall/tests/.DS_Store
biometall/tests/conftest.py
biometall/tests/test_biometall.py
biometall/tests/test_calculate_center_and_radius.py
biometall/tests/test_check_actual_motif.py
biometall/tests/test_check_possible_mutations.py
biometall/tests/test_chunk_size.py
biometall/tests/test_countersubset.py
biometall/tests/test_full_calculation.py
biometall/tests/test_grid.py
biometall/tests/test_parse_molecule.py
biometall/tests/data/.DS_Store
biometall/tests/data/1oi0.pdb
biometall/tests/data/1oi0_exception.pdb
biometall/tests/data/1oi0_output0.pdb
biometall/tests/data/1oi0_output0.txt
biometall/tests/data/1oi0_output1.pdb
biometall/tests/data/1oi0_output1.txt
biometall/tests/data/1oi0_output2.pdb
biometall/tests/data/1oi0_output2.txt
biometall/tests/data/1oi0_output3.pdb
biometall/tests/data/1oi0_output3.txt
biometall/tests/data/1oi0_output4.pdb
biometall/tests/data/1oi0_output4.txt
