Metadata-Version: 2.0
Name: BioMetAll
Version: 1.0
Summary: UNKNOWN
Home-page: UNKNOWN
Author: Insilichem
Author-email: joseemilio.sanchez@uab.cat
License: BSD-3-Clause
Platform: Linux
Platform: Mac OS-X
Platform: Unix
Platform: Windows
Requires-Python: >=3.5
Requires-Dist: numpy
Requires-Dist: psutil
